controllers/__init__.py
controllers/controller.py
core/__init__.py
core/router.py
core/server.py
core/auth/auth.py
core/data/foreign_key.py
database/__init__.py
database/database.py
dtos/__init__.py
dtos/dto.py
models/__init__.py
models/model.py
services/__init__.py
services/handler.py
magu_rest_in_peace-0.0.1.dist-info/METADATA
magu_rest_in_peace-0.0.1.dist-info/WHEEL
magu_rest_in_peace-0.0.1.dist-info/top_level.txt
magu_rest_in_peace-0.0.1.dist-info/RECORD
