Metadata-Version: 2.4
Name: magu-rest-in-peace
Version: 0.0.1
Summary: Simple Web Framework.
Requires-Dist: cffi
Requires-Dist: cryptography
Requires-Dist: pycparser
Requires-Dist: PyJWT
